gaia_control/__init__.py
gaia_control/gaia_control.py
gaia_control-0.1.8.dist-info/METADATA
gaia_control-0.1.8.dist-info/RECORD
gaia_control-0.1.8.dist-info/WHEEL
gaia_control-0.1.8.dist-info/entry_points.txt
gaia_control-0.1.8.dist-info/top_level.txt
tests/__init__.py
tests/test_placeholder.py
